rna_map/__init__.py
rna_map/bit_vector.py
rna_map/cli.py
rna_map/cli_opts.py
rna_map/exception.py
rna_map/external_cmd.py
rna_map/logger.py
rna_map/mapping.py
rna_map/mutation_histogram.py
rna_map/parameters.py
rna_map/run.py
rna_map/sam.py
rna_map/settings.py
rna_map/util.py
rna_map/resources/.DS_Store
rna_map/resources/bowtie2_args.csv
rna_map/resources/cli_opts.yml
rna_map/resources/default.yml
rna_map/resources/logo.txt
rna_map/resources/params_schema.json
rna_map/resources/phred_ascii.txt
rna_map/resources/picard.jar
rna_map/resources/presets/barcoded-library-large.yml
rna_map/resources/presets/barcoded-library.yml
rna_map-0.4.0.dist-info/LICENSE
rna_map-0.4.0.dist-info/METADATA
rna_map-0.4.0.dist-info/WHEEL
rna_map-0.4.0.dist-info/entry_points.txt
rna_map-0.4.0.dist-info/top_level.txt
rna_map-0.4.0.dist-info/RECORD
