Metadata-Version: 2.1
Name: rna-map
Version: 0.4.0
Summary: rapid analysis of RNA mutational profiling (MaP) experiments.
Home-page: https://github.com/YesselmanLab/rna_map
Author: Joe Yesselman
Author-email: jyesselm@unl.edu
Keywords: rna_map
Classifier: Intended Audience :: Developers
Classifier: Natural Language :: English
Classifier: Programming Language :: Python :: 3
Classifier: Programming Language :: Python :: Implementation :: PyPy
License-File: LICENSE
Requires-Dist: colorlog
Requires-Dist: click
Requires-Dist: cloup
Requires-Dist: plotly
Requires-Dist: matplotlib
Requires-Dist: numpy
Requires-Dist: pandas
Requires-Dist: tabulate
Requires-Dist: pyyaml
Requires-Dist: future
Requires-Dist: pytest
Requires-Dist: jsonschema
